ai_screenshot.py
ai_screenshooter-1.2.1.dist-info/METADATA
ai_screenshooter-1.2.1.dist-info/WHEEL
ai_screenshooter-1.2.1.dist-info/entry_points.txt
ai_screenshooter-1.2.1.dist-info/top_level.txt
ai_screenshooter-1.2.1.dist-info/RECORD
