Metadata-Version: 2.4
Name: ai-screenshooter
Version: 1.2.1
Summary: A CLI tool to capture and send AI-powered screenshots
Home-page: https://github.com/tech4vision/ai-screenshoter
Author: Last Shot AI
Author-email: support@lastshot.ai
Classifier: Programming Language :: Python :: 3
Classifier: License :: OSI Approved :: MIT License
Classifier: Operating System :: OS Independent
Requires-Python: >=3.6
Requires-Dist: pynput
Requires-Dist: requests
Requires-Dist: Pillow
Requires-Dist: pygetwindow
Dynamic: author
Dynamic: author-email
Dynamic: classifier
Dynamic: home-page
Dynamic: requires-dist
Dynamic: requires-python
Dynamic: summary
